organize_my_files-0.1.2.dist-info/licenses/LICENSE
organizer/__init__.py
organizer/cli.py
organizer/core.py
organize_my_files-0.1.2.dist-info/METADATA
organize_my_files-0.1.2.dist-info/WHEEL
organize_my_files-0.1.2.dist-info/entry_points.txt
organize_my_files-0.1.2.dist-info/top_level.txt
organize_my_files-0.1.2.dist-info/RECORD
